synphony_mcp/__init__.py
synphony_mcp/client.py
synphony_mcp/config.py
synphony_mcp/server.py
synphony_mcp-0.1.2.dist-info/METADATA
synphony_mcp-0.1.2.dist-info/WHEEL
synphony_mcp-0.1.2.dist-info/entry_points.txt
synphony_mcp-0.1.2.dist-info/top_level.txt
synphony_mcp-0.1.2.dist-info/RECORD
