Metadata-Version: 2.4
Name: synphony-mcp
Version: 0.1.2
Summary: MCP server for Synphony robotics data platform
Author-email: Synphony <dev@synphony.co>
License: MIT
Project-URL: Homepage, https://synphony.co
Project-URL: Documentation, https://synphony.co/docs
Project-URL: Repository, https://github.com/synphonyco/synphony-mcp
Keywords: mcp,robotics,video,data,synphony
Classifier: Development Status :: 3 - Alpha
Classifier: Intended Audience :: Developers
Classifier: License :: OSI Approved :: MIT License
Classifier: Programming Language :: Python :: 3
Classifier: Programming Language :: Python :: 3.10
Classifier: Programming Language :: Python :: 3.11
Classifier: Programming Language :: Python :: 3.12
Requires-Python: >=3.10
Requires-Dist: mcp>=1.0.0
Requires-Dist: httpx>=0.27.0
Provides-Extra: dev
Requires-Dist: pytest>=8.0.0; extra == "dev"
Requires-Dist: black>=24.0.0; extra == "dev"
